setup.cfg
setup.py
django_jsend/__init__.py
django_jsend.egg-info/PKG-INFO
django_jsend.egg-info/SOURCES.txt
django_jsend.egg-info/dependency_links.txt
django_jsend.egg-info/requires.txt
django_jsend.egg-info/top_level.txt