Metadata-Version: 1.1
Name: django-jsend
Version: 0.2
Summary: Django view for JSend specification
Home-page: https://github.com/krukas/django-jsend
Author: Maikel Martens
Author-email: maikel@martens.me
License: UNKNOWN
Download-URL: https://github.com/krukas/django-jsend/tarball/0.2
Keywords: Django,view,JSend
Platform: UNKNOWN
